nanonispy/__init__.py
nanonispy/constants.py
nanonispy/read.py
nanonispy-1.1.0.dist-info/LICENSE
nanonispy-1.1.0.dist-info/METADATA
nanonispy-1.1.0.dist-info/WHEEL
nanonispy-1.1.0.dist-info/top_level.txt
nanonispy-1.1.0.dist-info/RECORD
