Metadata-Version: 1.2
Name: nanonispy
Version: 1.1.0
Summary: Library to parse Nanonis files.
Home-page: https://github.com/underchemist/nanonispy
Author: Yann-Sebastien Tremblay-Johnston
Author-email: yanns.tremblay@gmail.com
License: MIT
Keywords: science numpy parse library
Platform: any
Classifier: Development Status :: 4 - Beta
Classifier: Intended Audience :: Science/Research
Classifier: Topic :: Scientific/Engineering :: Physics
Classifier: License :: OSI Approved :: MIT License
Classifier: Programming Language :: Python :: 3.6
Classifier: Programming Language :: Python :: 3.7
Classifier: Programming Language :: Python :: 3.8
Classifier: Programming Language :: Python :: 3.9
Requires-Python: >=3.6
